databoost/__init__.py
databoost/metrics/__init__.py
databoost/metrics/scos.py
databoost/nn/__init__.py
databoost/nn/trainnn.py
databoost/visuals/__init__.py
databoost/visuals/plotdecisionboundary.py
databoost/visuals/showactivationareas.py
databoost/visuals/showforwardpass.py
databoost-0.3.13.dist-info/licenses/LICENSE
databoost-0.3.13.dist-info/METADATA
databoost-0.3.13.dist-info/WHEEL
databoost-0.3.13.dist-info/top_level.txt
databoost-0.3.13.dist-info/RECORD
