Metadata-Version: 2.4
Name: databoost
Version: 0.3.13
Summary: Advanced Data Science utilities: custom metrics, advanced plotting, ML helpers, and more!
Author-email: Francesco Scolz <francesco.scolz@gmail.com>
License: MIT
License-File: LICENSE
Requires-Dist: numpy
Requires-Dist: pandas
Requires-Dist: matplotlib
Requires-Dist: seaborn
Requires-Dist: scikit-learn
Requires-Dist: torch
Dynamic: license-file
